synker/__init__.py
synker/kde.py
synker/kl_div.py
synker/pinkde.py
synker/scott.py
synker/silverman.py
synker/synthetic.py
synker-0.0.4.dist-info/LICENSE.txt
synker-0.0.4.dist-info/METADATA
synker-0.0.4.dist-info/WHEEL
synker-0.0.4.dist-info/top_level.txt
synker-0.0.4.dist-info/RECORD
