Metadata-Version: 2.2
Name: synker
Version: 0.0.4
Summary: A Python package for generating synthetic data.
Author-email: Danial Haselibozchaloee <dhaselib@gmail.com>
License: MIT License
Requires-Python: >=3.7
License-File: LICENSE.txt
Requires-Dist: numpy
Provides-Extra: dev
Requires-Dist: pytest; extra == "dev"
